Metadata-Version: 2.1
Name: cortx-pytorch
Version: 1.0.1
Summary: Fast interface between pytorch and Segate CORTX
Home-page: https://github.com/GuillaumeLeclerc/cortx_pytorch
Author: Guillaume Leclerc
Author-email: leclerc@mit.edu
License: UNKNOWN
Platform: UNKNOWN
